khulnasoft/__init__.py
khulnasoft/api_client.py
khulnasoft/exceptions.py
khulnasoft/py.typed
khulnasoft/version.py
khulnasoft-0.1.25.dist-info/LICENSE
khulnasoft-0.1.25.dist-info/METADATA
khulnasoft-0.1.25.dist-info/WHEEL
khulnasoft-0.1.25.dist-info/RECORD
