Metadata-Version: 2.1
Name: khulnasoft
Version: 0.1.25
Summary: Python SDK for the khulnasoft.com API.
Home-page: https://github.com/khulnasoft/python-khulnasoft
License: MIT
Keywords: khulnasoft,sdk
Author: Md Sulaiman
Author-email: dev.sulaiman@icloud.com
Requires-Python: >=3.8
Classifier: Intended Audience :: Developers
Classifier: Intended Audience :: Information Technology
Classifier: License :: OSI Approved :: MIT License
Classifier: Operating System :: POSIX :: Linux
Classifier: Programming Language :: Python :: 3
Classifier: Programming Language :: Python :: 3.8
Classifier: Programming Language :: Python :: 3.9
Classifier: Programming Language :: Python :: 3.10
Classifier: Programming Language :: Python :: 3.11
Classifier: Programming Language :: Python :: 3.12
Classifier: Topic :: Software Development :: Libraries :: Application Frameworks
Requires-Dist: requests (>=2)
Project-URL: Repository, https://github.com/khulnasoft/python-khulnasoft
